feathery/__init__.py
feathery/async_core.py
feathery/aws_core.py
feathery/command.py
feathery/component.py
feathery/gateway.py
feathery/multi_core.py
feathery/payload.py
feathery/service.py
feathery/shard.py
feathery_py-0.0.4.dist-info/LICENSE
feathery_py-0.0.4.dist-info/METADATA
feathery_py-0.0.4.dist-info/WHEEL
feathery_py-0.0.4.dist-info/top_level.txt
feathery_py-0.0.4.dist-info/RECORD
