Metadata-Version: 2.1
Name: feathery-py
Version: 0.0.4
Summary: No description yet
Home-page: https://github.com/NotOddity/feathery
Author: NotOddity
License: UNKNOWN
Platform: UNKNOWN
License-File: LICENSE
